stix2arango/__init__.py
stix2arango/__main__.py
stix2arango/config.py
stix2arango/utils.py
stix2arango/services/__init__.py
stix2arango/services/arangodb_service.py
stix2arango/services/version_annotator.py
stix2arango/stix2arango/__init__.py
stix2arango/stix2arango/bundle_loader.py
stix2arango/stix2arango/stix2arango.py
stix2arango/templates/marking-definition.json
stix2arango-1.1.13.dist-info/METADATA
stix2arango-1.1.13.dist-info/WHEEL
stix2arango-1.1.13.dist-info/entry_points.txt
stix2arango-1.1.13.dist-info/licenses/LICENSE
stix2arango-1.1.13.dist-info/RECORD
