Metadata-Version: 2.4
Name: stix2arango
Version: 1.1.13
Summary: stix2arango is a command line tool that takes a group of STIX 2.1 objects in a bundle and inserts them into ArangoDB. It can also handle updates to existing objects in ArangoDB imported in a bundle.
Project-URL: Homepage, https://github.com/muchdogesec/stix2arango
Project-URL: Issues, https://github.com/muchdogesec/stix2arango/issues
Project-URL: dogesec HQ, https://dogesec.com
Author: dogesec
Maintainer: dogesec
License-File: LICENSE
Classifier: License :: OSI Approved :: Apache Software License
Classifier: Operating System :: OS Independent
Classifier: Programming Language :: Python :: 3
Requires-Python: >=3.9
Requires-Dist: ijson>=3.4.0
Requires-Dist: jsonschema>=4.22.0; python_version >= '3.8'
Requires-Dist: python-arango>=8.1.3; python_version >= '3.8'
Requires-Dist: python-dotenv>=1.0.1
Requires-Dist: requests>=2.31.0; python_version >= '3.7'
Requires-Dist: stix2
Requires-Dist: tqdm>=4.66.4; python_version >= '3.7'
